space_phot/MIRIMBkgInterp.py
space_phot/__init__.py
space_phot/cal.py
space_phot/photometry.py
space_phot/util.py
space_phot/wfc3_photometry/photometry_tools/__init__.py
space_phot/wfc3_photometry/photometry_tools/background_median.py
space_phot/wfc3_photometry/photometry_tools/phot_wrapper.py
space_phot/wfc3_photometry/photometry_tools/photometry_with_errors.py
space_phot/wfc3_photometry/photometry_tools/rad_prof.py
space_phot/wfc3_photometry/photometry_tools/__pycache__/__init__.cpython-310.pyc
space_phot/wfc3_photometry/photometry_tools/__pycache__/__init__.cpython-311.pyc
space_phot/wfc3_photometry/photometry_tools/__pycache__/__init__.cpython-37.pyc
space_phot/wfc3_photometry/photometry_tools/__pycache__/__init__.cpython-38.pyc
space_phot/wfc3_photometry/photometry_tools/__pycache__/background_median.cpython-310.pyc
space_phot/wfc3_photometry/photometry_tools/__pycache__/background_median.cpython-311.pyc
space_phot/wfc3_photometry/photometry_tools/__pycache__/background_median.cpython-37.pyc
space_phot/wfc3_photometry/photometry_tools/__pycache__/background_median.cpython-38.pyc
space_phot/wfc3_photometry/photometry_tools/__pycache__/phot_wrapper.cpython-310.pyc
space_phot/wfc3_photometry/photometry_tools/__pycache__/phot_wrapper.cpython-311.pyc
space_phot/wfc3_photometry/photometry_tools/__pycache__/phot_wrapper.cpython-37.pyc
space_phot/wfc3_photometry/photometry_tools/__pycache__/phot_wrapper.cpython-38.pyc
space_phot/wfc3_photometry/photometry_tools/__pycache__/photometry_with_errors.cpython-310.pyc
space_phot/wfc3_photometry/photometry_tools/__pycache__/photometry_with_errors.cpython-311.pyc
space_phot/wfc3_photometry/photometry_tools/__pycache__/photometry_with_errors.cpython-37.pyc
space_phot/wfc3_photometry/photometry_tools/__pycache__/photometry_with_errors.cpython-38.pyc
space_phot/wfc3_photometry/photometry_tools/__pycache__/rad_prof.cpython-310.pyc
space_phot/wfc3_photometry/photometry_tools/__pycache__/rad_prof.cpython-311.pyc
space_phot-0.4.0.dist-info/METADATA
space_phot-0.4.0.dist-info/WHEEL
space_phot-0.4.0.dist-info/top_level.txt
space_phot-0.4.0.dist-info/RECORD
