Metadata-Version: 2.4
Name: space_phot
Version: 0.4.0
Summary: Aperture and PSF photometry tools for HST and JWST data.
Author: Justin Pierel
Author-email: Justin Pierel <jpierel@stsci.edu>
Project-URL: Homepage, https://space-phot.readthedocs.io/en/latest/
Requires-Python: >=3.11
Requires-Dist: numpy>=1.23
Requires-Dist: scipy>=1.9
Requires-Dist: astropy>=7.1.1
Requires-Dist: photutils>=2.3
Requires-Dist: matplotlib>=3.7
Requires-Dist: sncosmo>=2.12.1
Requires-Dist: dynesty>=3.0.0
Requires-Dist: dill>=0.3.6
Requires-Dist: corner>=2.2
Requires-Dist: stpsf>=2.1
Requires-Dist: poppy>=1.1.2
Requires-Dist: stsci.skypac>=1.0.11
Requires-Dist: jwst>=1.19
Requires-Dist: stdatamodels>=4.0.1
Requires-Dist: stpipe>=0.10.0
Requires-Dist: gwcs>=0.25.2
Requires-Dist: asdf>=4.5.0
Provides-Extra: test
Requires-Dist: pytest>=7.4; extra == "test"
Requires-Dist: pytest-cov>=4.1; extra == "test"
Provides-Extra: docs
Requires-Dist: sphinx>=7; extra == "docs"
Requires-Dist: sphinx-rtd-theme; extra == "docs"
Requires-Dist: sphinx-gallery; extra == "docs"
Requires-Dist: numpydoc; extra == "docs"
Requires-Dist: sphinx-exec-code; extra == "docs"
Requires-Dist: astroquery; extra == "docs"
Provides-Extra: dev
Requires-Dist: ruff>=0.5; extra == "dev"
Requires-Dist: black>=24.3; extra == "dev"
Requires-Dist: isort>=5.13; extra == "dev"
Requires-Dist: pre-commit>=3.7; extra == "dev"
Dynamic: author
